fgobjlib/__init__.py
fgobjlib/fg_fw_address.py
fgobjlib/fg_fw_addrgrp.py
fgobjlib/fg_fw_policy.py
fgobjlib/fg_fw_service.py
fgobjlib/fg_object.py
fgobjlib/fg_sys_interface.py
fgobjlib/fg_sys_router_static.py
fgobjlib/fg_sys_vdom.py
fgobjlib/fg_sys_vdomlink.py
fgobjlib/fg_vpn_ipsec_p1_interface.py
fgobjlib/fg_vpn_ipsec_p2_interface.py
pyFGT/__init__.py
pyFGT/fortigate.py
pyfgt-0.5.7.dist-info/licenses/LICENSE
pyfgt-0.5.7.dist-info/METADATA
pyfgt-0.5.7.dist-info/WHEEL
pyfgt-0.5.7.dist-info/top_level.txt
pyfgt-0.5.7.dist-info/RECORD
