Metadata-Version: 2.4
Name: pyfgt
Version: 0.5.7
Summary: Represents the base components of the Fortinet FortiGate REST interface with abstractions
Home-page: https://github.com/p4r4n0y1ng/pyfgt
Author: p4r4n0y1ng
Author-email: jhuber@fortinet.com
License: Apache 2.0
License-File: LICENSE
Requires-Dist: requests
Dynamic: author
Dynamic: author-email
Dynamic: description
Dynamic: description-content-type
Dynamic: home-page
Dynamic: license
Dynamic: license-file
Dynamic: requires-dist
Dynamic: summary
